asmagic/__init__.py
asmagic/arDataSubscriber.py
asmagic/data_types.py
asmagic/imuDataSubscriber.py
asmagic/joystickDataSubscriber.py
asmagic/py.typed
asmagic/proto/__init__.py
asmagic/proto/imu_msg_pb2.py
asmagic/proto/joystick_msg_pb2.py
asmagic/proto/phone_msg_pb2.py
asmagic-0.1.4.dist-info/METADATA
asmagic-0.1.4.dist-info/WHEEL
asmagic-0.1.4.dist-info/top_level.txt
asmagic-0.1.4.dist-info/RECORD
