Metadata-Version: 2.4
Name: asmagic
Version: 0.1.4
Summary: AR and IMU Sensor Data Magic Library - Subscribe to AR and IMU sensor data streams
Author: ASMagic Team
Project-URL: Homepage, https://github.com/asmagic/asmagic
Project-URL: Documentation, https://github.com/asmagic/asmagic#readme
Project-URL: Repository, https://github.com/asmagic/asmagic
Project-URL: Issues, https://github.com/asmagic/asmagic/issues
Keywords: ar,imu,sensor,zmq,protobuf,streaming,accelerometer,gyroscope
Classifier: Development Status :: 4 - Beta
Classifier: Intended Audience :: Developers
Classifier: License :: OSI Approved :: MIT License
Classifier: Operating System :: OS Independent
Classifier: Programming Language :: Python :: 3
Classifier: Programming Language :: Python :: 3.8
Classifier: Programming Language :: Python :: 3.9
Classifier: Programming Language :: Python :: 3.10
Classifier: Programming Language :: Python :: 3.11
Classifier: Programming Language :: Python :: 3.12
Classifier: Topic :: Scientific/Engineering
Requires-Python: >=3.8
Requires-Dist: numpy>=1.20.0
Requires-Dist: pyzmq>=22.0.0
Requires-Dist: protobuf>=4.0.0
Requires-Dist: opencv-python>=4.5.0
Requires-Dist: Pillow>=8.0.0
Provides-Extra: dev
Requires-Dist: pytest>=7.0.0; extra == "dev"
Requires-Dist: black>=22.0.0; extra == "dev"
Requires-Dist: mypy>=0.990; extra == "dev"
